discord_rpc/__init__.py
discord_rpc/codes/__init__.py
discord_rpc/codes/errorcodes.py
discord_rpc/codes/opcodes.py
discord_rpc/codes/statecodes.py
discord_rpc/connection/__init__.py
discord_rpc/connection/ipc.py
discord_rpc/connection/rpc.py
discord_rpc/util/__init__.py
discord_rpc/util/backoff.py
discord_rpc/util/limits.py
discord_rpc/util/types.py
discord_rpc/util/utils.py
discord_rpc.py-1.3.0.dist-info/LICENSE
discord_rpc.py-1.3.0.dist-info/METADATA
discord_rpc.py-1.3.0.dist-info/WHEEL
discord_rpc.py-1.3.0.dist-info/top_level.txt
discord_rpc.py-1.3.0.dist-info/RECORD
