Metadata-Version: 2.1
Name: discord-rpc.py
Version: 1.3.0
Summary: A Discord Rich Presence library for Python 2 & 3
Home-page: https://gitlab.com/somberdemise/discord-rpc.py
Author: Gustavo (somberdemise)
Author-email: me@gustavo.dev
License: Mozilla Public License 2.0 (MPL 2.0)
Platform: Windows
Platform: Linux
Platform: OSX
Classifier: Development Status :: 5 - Production/Stable
Classifier: License :: OSI Approved :: Mozilla Public License 2.0 (MPL 2.0)
Classifier: Programming Language :: Python :: 2.7
Classifier: Programming Language :: Python :: 3
Classifier: Programming Language :: Python :: Implementation :: CPython
Classifier: Operating System :: Microsoft :: Windows
Classifier: Operating System :: POSIX :: Linux
Classifier: Operating System :: MacOS :: MacOS X
Classifier: Intended Audience :: Developers
Classifier: Topic :: Software Development :: Libraries :: Python Modules
Classifier: Topic :: Software Development :: Libraries
